odoo10_addon_l10n_ec_ote-10.0.1.0.0-py2.7-nspkg.pth
odoo/addons/l10n_ec_ote/README.rst
odoo/addons/l10n_ec_ote/__init__.py
odoo/addons/l10n_ec_ote/__manifest__.py
odoo/addons/l10n_ec_ote/data/l10n_ec_ote.canton.csv
odoo/addons/l10n_ec_ote/data/l10n_ec_ote.parish.csv
odoo/addons/l10n_ec_ote/data/res.country.state.csv
odoo/addons/l10n_ec_ote/data/res_country.xml
odoo/addons/l10n_ec_ote/models/__init__.py
odoo/addons/l10n_ec_ote/models/ote.py
odoo/addons/l10n_ec_ote/models/res_partner.py
odoo/addons/l10n_ec_ote/security/ir.model.access.csv
odoo/addons/l10n_ec_ote/static/description/icon.png
odoo/addons/l10n_ec_ote/views/res_partner.xml
odoo10_addon_l10n_ec_ote-10.0.1.0.0.dist-info/DESCRIPTION.rst
odoo10_addon_l10n_ec_ote-10.0.1.0.0.dist-info/METADATA
odoo10_addon_l10n_ec_ote-10.0.1.0.0.dist-info/RECORD
odoo10_addon_l10n_ec_ote-10.0.1.0.0.dist-info/WHEEL
odoo10_addon_l10n_ec_ote-10.0.1.0.0.dist-info/metadata.json
odoo10_addon_l10n_ec_ote-10.0.1.0.0.dist-info/namespace_packages.txt
odoo10_addon_l10n_ec_ote-10.0.1.0.0.dist-info/top_level.txt
